{
	"timeList50": [
		{
			"state": "1",
			"content": "跑步中"
		},{
			"state": "2",
			"content": "跑步中(登录)"
		},{
			"state": "3",
			"content": "在线"
		},{
			"state": "4",
			"content": "离线"
		},{
			"state": "5",
			"content": "在线(登录)"
		},{
			"state": "5",
			"content": "在线(登录)"
		},{
			"state": "5",
			"content": "在线(登录)"
		},{
			"state": "5",
			"content": "在线(登录)"
		}
	],
	"timeList51": [
		{
			"state": "1",
			"content": "跑步中"
		},{
			"state": "2",
			"content": "跑步中(登录)"
		},{
			"state": "3",
			"content": "在线"
		},{
			"state": "4",
			"content": "离线"
		},{
			"state": "2",
			"content": "跑步中(登录)"
		},{
			"state": "3",
			"content": "在线"
		}
	],"timeList52": [
		{
			"state": "1",
			"content": "跑步中"
		},{
			"state": "2",
			"content": "跑步中(登录)"
		},{
			"state": "3",
			"content": "在线"
		},{
			"state": "4",
			"content": "离线"
		},{
			"state": "5",
			"content": "在线(登录)"
		},{
			"state": "5",
			"content": "在线(登录)"
		},{
			"state": "5",
			"content": "在线(登录)"
		},{
			"state": "5",
			"content": "在线(登录)"
		}
	],"timeList53": [
		{
			"state": "1",
			"content": "跑步中"
		},{
			"state": "2",
			"content": "跑步中(登录)"
		},{
			"state": "3",
			"content": "在线"
		},{
			"state": "4",
			"content": "离线"
		},{
			"state": "5",
			"content": "在线(登录)"
		},{
			"state": "5",
			"content": "在线(登录)"
		}
	],"timeList54": [
		{
			"state": "1",
			"content": "跑步中"
		}
	],"timeList55": [
		{
			"state": "1",
			"content": "跑步中"
		},{
			"state": "5",
			"content": "在线(登录)"
		},{
			"state": "5",
			"content": "在线(登录)"
		},{
			"state": "5",
			"content": "在线(登录)"
		}
	],"timeList56": [
		{
			"state": "1",
			"content": "跑步中"
		},{
			"state": "2",
			"content": "跑步中(登录)"
		},{
			"state": "3",
			"content": "在线"
		}
	]
}